luml/__init__.py
luml/_constants.py
luml/modelref.py
luml/api/__init__.py
luml/api/_base_client.py
luml/api/_client.py
luml/api/_exceptions.py
luml/api/_types.py
luml/api/_utils.py
luml/api/py.typed
luml/api/resources/__init__.py
luml/api/resources/_validators.py
luml/api/resources/bucket_secrets.py
luml/api/resources/collections.py
luml/api/resources/model_artifacts.py
luml/api/resources/orbits.py
luml/api/resources/organizations.py
luml/api/services/upload_service.py
luml/api/utils/__init__.py
luml/api/utils/azure_file_handler.py
luml/api/utils/base_file_handler.py
luml/api/utils/file_handler_factory.py
luml/api/utils/model_artifacts.py
luml/api/utils/s3_file_handler.py
luml/experiments/tracker.py
luml/experiments/utils.py
luml/experiments/backends/__init__.py
luml/experiments/backends/_base.py
luml/experiments/backends/sqlite.py
luml/experiments/tracing/__init__.py
luml/experiments/tracing/span_exporter.py
luml/integrations/__init__.py
luml/integrations/langgraph/__init__.py
luml/integrations/langgraph/packaging/__init__.py
luml/integrations/langgraph/packaging/_templates/mermaid.py
luml/integrations/langgraph/packaging/_templates/pyfunc.py
luml/integrations/sklearn/__init__.py
luml/integrations/sklearn/packaging/__init__.py
luml/integrations/sklearn/packaging/_template.py
luml/model_card/__init__.py
luml/model_card/builder.py
luml/model_card/templates.py
luml/utils/deps.py
luml/utils/imports.py
luml/utils/tar.py
luml/utils/time.py
luml_sdk-0.1.0rc2.dist-info/METADATA
luml_sdk-0.1.0rc2.dist-info/WHEEL
luml_sdk-0.1.0rc2.dist-info/entry_points.txt
luml_sdk-0.1.0rc2.dist-info/RECORD
