Metadata-Version: 2.4
Name: luml_sdk
Version: 0.1.0rc2
Summary: LUML Python SDK
Requires-Python: >=3.12
Requires-Dist: pyfnx-utils<1.0.0,>=0.0.1
Provides-Extra: api
Requires-Dist: httpx<1.0.0,>=0.28.1; extra == 'api'
Requires-Dist: pydantic<3.0.0,>=2.11.7; extra == 'api'
Provides-Extra: core
Requires-Dist: cloudpickle<4.0.0,>=3.1.2; extra == 'core'
Requires-Dist: fnnx<0.1.0,>=0.0.8; extra == 'core'
Requires-Dist: pydantic<3.0.0,>=2.11.7; extra == 'core'
Provides-Extra: tracing
Requires-Dist: opentelemetry-api>=1.36.0; extra == 'tracing'
Requires-Dist: opentelemetry-instrumentation-openai>=0.44.1; extra == 'tracing'
Requires-Dist: opentelemetry-sdk>=1.36.0; extra == 'tracing'
